gitlab_users/__init__.py
gitlab_users/cli.py
gitlab_users/models.py
gitlab_users/services.py
gitlab_users/utils.py
gitlab_users-2.0.1.dist-info/licenses/LICENSE
gitlab_users-2.0.1.dist-info/METADATA
gitlab_users-2.0.1.dist-info/WHEEL
gitlab_users-2.0.1.dist-info/entry_points.txt
gitlab_users-2.0.1.dist-info/top_level.txt
gitlab_users-2.0.1.dist-info/RECORD
