Metadata-Version: 2.4
Name: gitlab-users
Version: 2.0.1
Summary: Export GitLab users information and automate user accounts creation
Author-email: Matthieu Boileau <matthieu.boileau@math.unistra.fr>
License: MIT
Project-URL: Homepage, https://github.com/boileaum/gitlab-users
Project-URL: Repository, https://github.com/boileaum/gitlab-users
Project-URL: Documentation, https://gitlab-users.readthedocs.io
Project-URL: Changelog, https://github.com/boileaum/gitlab-users/blob/main/CHANGELOG.md
Classifier: Programming Language :: Python :: 3
Classifier: Operating System :: OS Independent
Requires-Python: >=3.9
License-File: LICENSE
Requires-Dist: python-gitlab>=5.0.0
Provides-Extra: dev
Requires-Dist: ruff; extra == "dev"
Requires-Dist: black; extra == "dev"
Requires-Dist: pytest; extra == "dev"
Requires-Dist: pytest-cov; extra == "dev"
Requires-Dist: build; extra == "dev"
Requires-Dist: pre-commit; extra == "dev"
Dynamic: license-file
